{
  "title": "Open Science Hackathon",
  "subtitle": "Live leaderboard for science project teams",
  "customCss": "css/styles.css",
  "paging": {
    "enabled": true,
    "itemsPerPage": 5
  },
  "columns": [
    {
      "field": "position",
      "label": "Place",
      "class": "position"
    },
    {
      "field": "icon",
      "label": "Logo",
      "class": "icon"
    },
    {
      "field": "teamName",
      "label": "Team Name",
      "class": "team"
    },
    {
      "field": "score",
      "label": "Points",
      "class": "points"
    },
    {
      "field": "project",
      "label": "Project",
      "class": "project"
    },
    {
      "field": "country",
      "label": "Country",
      "class": "country"
    }
  ],
  "teams": [
    {
      "id": 1,
      "teamName": "BioInnovators",
      "score": 1200,
      "lastUpdate": "2025-07-22",
  "icon": "https://cdn.jsdelivr.net/npm/bootstrap-icons@1.11.3/icons/bezier.svg",
      "project": "DNA Data Storage",
      "country": "USA",
      "members": ["Alice", "Bob"]
    },
    {
      "id": 2,
      "teamName": "QuantumLeap",
      "score": 1150,
      "lastUpdate": "2025-07-22",
  "icon": "https://cdn.jsdelivr.net/npm/bootstrap-icons@1.11.3/icons/cpu.svg",
      "project": "Quantum Computing Simulator",
      "country": "Germany",
      "members": ["Clara", "David"]
    },
    {
      "id": 3,
      "teamName": "EcoCoders",
      "score": 1100,
      "lastUpdate": "2025-07-21",
  "icon": "https://cdn.jsdelivr.net/npm/bootstrap-icons@1.11.3/icons/tree.svg",
      "project": "AI for Reforestation",
      "country": "Brazil",
      "members": ["Eva", "Felipe"]
    },
    {
      "id": 4,
      "teamName": "AstroBytes",
      "score": 1050,
      "lastUpdate": "2025-07-21",
  "icon": "https://cdn.jsdelivr.net/npm/bootstrap-icons@1.11.3/icons/moon-stars.svg",
      "project": "Satellite Image Analysis",
      "country": "India",
      "members": ["Gita", "Hari"]
    },
    {
      "id": 5,
      "teamName": "MedTechX",
      "score": 1000,
      "lastUpdate": "2025-07-20",
  "icon": "https://cdn.jsdelivr.net/npm/bootstrap-icons@1.11.3/icons/heart-pulse.svg",
      "project": "Remote Health Monitoring",
      "country": "UK",
      "members": ["Ivy", "Jack"]
    }
  ]
}
